dtflow/SKILL.md
dtflow/__init__.py
dtflow/__main__.py
dtflow/converters.py
dtflow/core.py
dtflow/framework.py
dtflow/lineage.py
dtflow/parallel.py
dtflow/pipeline.py
dtflow/presets.py
dtflow/schema.py
dtflow/streaming.py
dtflow/tokenizers.py
dtflow/cli/__init__.py
dtflow/cli/clean.py
dtflow/cli/commands.py
dtflow/cli/common.py
dtflow/cli/io_ops.py
dtflow/cli/lineage.py
dtflow/cli/pipeline.py
dtflow/cli/sample.py
dtflow/cli/skill.py
dtflow/cli/stats.py
dtflow/cli/transform.py
dtflow/cli/validate.py
dtflow/storage/__init__.py
dtflow/storage/io.py
dtflow/utils/__init__.py
dtflow/utils/display.py
dtflow/utils/field_path.py
dtflow/utils/helpers.py
dtflow-0.5.8.dist-info/METADATA
dtflow-0.5.8.dist-info/WHEEL
dtflow-0.5.8.dist-info/entry_points.txt
dtflow-0.5.8.dist-info/RECORD
