Metadata-Version: 2.4
Name: dtflow
Version: 0.5.8
Summary: A flexible data transformation tool for ML training formats (SFT, RLHF, Pretrain)
Project-URL: Homepage, https://github.com/yourusername/DataTransformer
Project-URL: Documentation, https://github.com/yourusername/DataTransformer#readme
Project-URL: Repository, https://github.com/yourusername/DataTransformer
Project-URL: Issues, https://github.com/yourusername/DataTransformer/issues
Project-URL: Changelog, https://github.com/yourusername/DataTransformer/blob/main/CHANGELOG.md
Author-email: Your Name <your.email@example.com>
Maintainer-email: Your Name <your.email@example.com>
License-Expression: MIT
Keywords: ai,data-processing,data-transformation,machine-learning,nlp,pretrain,rlhf,sft
Classifier: Development Status :: 4 - Beta
Classifier: Intended Audience :: Developers
Classifier: Intended Audience :: Science/Research
Classifier: License :: OSI Approved :: MIT License
Classifier: Operating System :: OS Independent
Classifier: Programming Language :: Python :: 3
Classifier: Programming Language :: Python :: 3.7
Classifier: Programming Language :: Python :: 3.8
Classifier: Programming Language :: Python :: 3.9
Classifier: Programming Language :: Python :: 3.10
Classifier: Programming Language :: Python :: 3.11
Classifier: Programming Language :: Python :: 3.12
Classifier: Topic :: Scientific/Engineering :: Artificial Intelligence
Classifier: Topic :: Software Development :: Libraries :: Python Modules
Classifier: Topic :: Text Processing
Requires-Python: >=3.8
Requires-Dist: numpy>=1.20.0
Requires-Dist: orjson>=3.9.0
Requires-Dist: polars>=0.20.0
Requires-Dist: pyyaml>=5.4.0
Requires-Dist: rich>=10.0.0
Requires-Dist: tiktoken>=0.5.0
Requires-Dist: typer>=0.9.0
Provides-Extra: converters
Requires-Dist: datasets>=2.0.0; extra == 'converters'
Provides-Extra: dev
Requires-Dist: black>=21.0; extra == 'dev'
Requires-Dist: datasets>=2.0.0; extra == 'dev'
Requires-Dist: datasketch>=1.5.0; extra == 'dev'
Requires-Dist: flake8>=3.9.0; extra == 'dev'
Requires-Dist: huggingface-hub>=0.20.0; extra == 'dev'
Requires-Dist: isort>=5.9.0; extra == 'dev'
Requires-Dist: mypy>=0.910; extra == 'dev'
Requires-Dist: pyarrow; extra == 'dev'
Requires-Dist: pytest-cov>=2.12.0; extra == 'dev'
Requires-Dist: pytest>=6.0.0; extra == 'dev'
Requires-Dist: rich>=10.0.0; extra == 'dev'
Requires-Dist: scikit-learn>=0.24.0; extra == 'dev'
Requires-Dist: tiktoken>=0.5.0; extra == 'dev'
Requires-Dist: tokenizers>=0.15.0; extra == 'dev'
Requires-Dist: toolong>=1.5.0; extra == 'dev'
Provides-Extra: display
Provides-Extra: docs
Requires-Dist: myst-parser>=0.15.0; extra == 'docs'
Requires-Dist: sphinx-rtd-theme>=0.5.0; extra == 'docs'
Requires-Dist: sphinx>=4.0.0; extra == 'docs'
Provides-Extra: full
Requires-Dist: datasets>=2.0.0; extra == 'full'
Requires-Dist: datasketch>=1.5.0; extra == 'full'
Requires-Dist: huggingface-hub>=0.20.0; extra == 'full'
Requires-Dist: pyarrow; extra == 'full'
Requires-Dist: rich>=10.0.0; extra == 'full'
Requires-Dist: scikit-learn>=0.24.0; extra == 'full'
Requires-Dist: tiktoken>=0.5.0; extra == 'full'
Requires-Dist: tokenizers>=0.15.0; extra == 'full'
Requires-Dist: toolong>=1.5.0; extra == 'full'
Provides-Extra: logs
Requires-Dist: toolong>=1.5.0; extra == 'logs'
Provides-Extra: similarity
Requires-Dist: datasketch>=1.5.0; extra == 'similarity'
Requires-Dist: scikit-learn>=0.24.0; extra == 'similarity'
Provides-Extra: storage
Requires-Dist: pyarrow; extra == 'storage'
Provides-Extra: tokenizers
Requires-Dist: tiktoken>=0.5.0; extra == 'tokenizers'
Provides-Extra: tokenizers-hf
Requires-Dist: huggingface-hub>=0.20.0; extra == 'tokenizers-hf'
Requires-Dist: tiktoken>=0.5.0; extra == 'tokenizers-hf'
Requires-Dist: tokenizers>=0.15.0; extra == 'tokenizers-hf'
